{
  "config": {
    "title": "Kpi Dashboard",
    "description": "My awesome app using docz",
    "menu": [],
    "version": "0.1.1",
    "repository": null,
    "native": false,
    "themeConfig": {},
    "separator": "-"
  },
  "entries": [
    {
      "key": "src/docs/Button.mdx",
      "value": {
        "name": "Button",
        "id": "9a8e43b05e308e45dbea894b4b1a9511",
        "filepath": "src/docs/Button.mdx",
        "fullpath": "/Users/account/Documents/code/office/cudy/kpi-dashboard/src/docs/Button.mdx",
        "link": "",
        "slug": "src-docs-button",
        "route": "/src-docs-button",
        "menu": "",
        "headings": [
          {
            "slug": "button",
            "depth": 1,
            "value": "Button"
          }
        ]
      }
    }
  ],
  "props": [
    {
      "key": "src/App.js",
      "value": [
        {
          "description": "",
          "displayName": "App",
          "methods": [],
          "actualName": "App"
        }
      ]
    },
    {
      "key": "src/components/BarChart.js",
      "value": [
        {
          "description": "",
          "displayName": "BarChart",
          "methods": [],
          "actualName": "BarChart",
          "props": {
            "domainPadding": {
              "defaultValue": {
                "value": "10",
                "computed": false
              },
              "required": false
            }
          }
        }
      ]
    },
    {
      "key": "src/components/Button.js",
      "value": [
        {
          "description": "",
          "displayName": "Button",
          "methods": [],
          "actualName": "Button"
        }
      ]
    },
    {
      "key": "src/components/ButtonLink.js",
      "value": [
        {
          "description": "",
          "displayName": "ButtonLink",
          "methods": [],
          "actualName": "ButtonLink"
        }
      ]
    },
    {
      "key": "src/components/Card.js",
      "value": [
        {
          "description": "",
          "displayName": "Card",
          "methods": [],
          "actualName": "Card"
        }
      ]
    },
    {
      "key": "src/components/ChartCard.js",
      "value": [
        {
          "description": "",
          "displayName": "ChartCard",
          "methods": [],
          "actualName": "ChartCard",
          "props": {
            "expander": {
              "defaultValue": {
                "value": "true",
                "computed": false
              },
              "required": false
            }
          }
        }
      ]
    },
    {
      "key": "src/components/Heading.js",
      "value": [
        {
          "description": "",
          "displayName": "Heading",
          "methods": [],
          "actualName": "Heading"
        }
      ]
    },
    {
      "key": "src/components/Layout.js",
      "value": [
        {
          "description": "",
          "displayName": "Layout",
          "methods": [],
          "actualName": "Layout",
          "props": {
            "basic": {
              "defaultValue": {
                "value": "false",
                "computed": false
              },
              "required": false
            },
            "sidebar": {
              "defaultValue": {
                "value": "false",
                "computed": false
              },
              "required": false
            },
            "breadcrumb": {
              "defaultValue": {
                "value": "false",
                "computed": false
              },
              "required": false
            },
            "location": {
              "defaultValue": {
                "value": "{}",
                "computed": false
              },
              "required": false
            }
          }
        }
      ]
    },
    {
      "key": "src/components/Loading.js",
      "value": [
        {
          "description": "",
          "displayName": "Loading",
          "methods": [],
          "actualName": "Loading"
        }
      ]
    },
    {
      "key": "src/components/Logo.js",
      "value": [
        {
          "description": "",
          "displayName": "Logo",
          "methods": [],
          "actualName": "Logo",
          "props": {
            "type": {
              "defaultValue": {
                "value": "\"solid\"",
                "computed": false
              },
              "required": false
            }
          }
        }
      ]
    },
    {
      "key": "src/components/Navbar.js",
      "value": [
        {
          "description": "",
          "displayName": "Navbar",
          "methods": [],
          "actualName": "Navbar"
        }
      ]
    },
    {
      "key": "src/components/Section.js",
      "value": [
        {
          "description": "",
          "displayName": "Section",
          "methods": [],
          "actualName": "Section"
        }
      ]
    },
    {
      "key": "src/components/Fields/SelectInput.js",
      "value": [
        {
          "description": "",
          "displayName": "SelectInput",
          "methods": [],
          "actualName": "SelectInput"
        }
      ]
    },
    {
      "key": "src/components/Fields/TextInput.js",
      "value": [
        {
          "description": "",
          "displayName": "TextInput",
          "methods": [],
          "actualName": "TextInput"
        }
      ]
    },
    {
      "key": "src/components/Fields/ToggleInput.js",
      "value": [
        {
          "description": "",
          "displayName": "ToggleInput",
          "methods": [],
          "actualName": "ToggleInput",
          "props": {
            "helpText": {
              "defaultValue": {
                "value": "\"\"",
                "computed": false
              },
              "required": false
            }
          }
        }
      ]
    },
    {
      "key": "src/components/Icons/Bag.js",
      "value": [
        {
          "description": "",
          "displayName": "BagIcon",
          "methods": [],
          "actualName": "BagIcon"
        }
      ]
    },
    {
      "key": "src/components/Icons/Homeware.js",
      "value": [
        {
          "description": "",
          "displayName": "HomewareIcon",
          "methods": [],
          "actualName": "HomewareIcon"
        }
      ]
    },
    {
      "key": "src/components/Icons/Lingerie.js",
      "value": [
        {
          "description": "",
          "displayName": "LingerieIcon",
          "methods": [],
          "actualName": "LingerieIcon"
        }
      ]
    },
    {
      "key": "src/components/Icons/Shoes.js",
      "value": [
        {
          "description": "",
          "displayName": "ShoesIcon",
          "methods": [],
          "actualName": "ShoesIcon"
        }
      ]
    },
    {
      "key": "src/components/Icons/Wallet.js",
      "value": [
        {
          "description": "",
          "displayName": "WalletIcon",
          "methods": [],
          "actualName": "WalletIcon"
        }
      ]
    },
    {
      "key": "src/components/StatCard.js",
      "value": [
        {
          "description": "",
          "displayName": "StatCard",
          "methods": [],
          "actualName": "StatCard",
          "props": {
            "title": {
              "defaultValue": {
                "value": "\"\"",
                "computed": false
              },
              "required": false
            },
            "value": {
              "defaultValue": {
                "value": "0",
                "computed": false
              },
              "required": false
            },
            "roleData": {
              "defaultValue": {
                "value": "{}",
                "computed": false
              },
              "required": false
            }
          }
        }
      ]
    }
  ]
}
